<annotation>
  <folder></folder>
  <filename>Mango00487.png</filename>
  <source>
    <database>Unknown</database>
    <annotation>Unknown</annotation>
    <image>Unknown</image>
  </source>
  <size>
    <width>320</width>
    <height>258</height>
    <depth></depth>
  </size>
  <segmented>0</segmented>
  <object>
    <name>Mango</name>
    <occluded>0</occluded>
    <bndbox>
      <xmin>0.0</xmin>
      <ymin>151.2</ymin>
      <xmax>52.3</xmax>
      <ymax>200.2</ymax>
    </bndbox>
  </object>
  <object>
    <name>Mango</name>
    <occluded>0</occluded>
    <bndbox>
      <xmin>0.0</xmin>
      <ymin>69.8</ymin>
      <xmax>79.2</xmax>
      <ymax>162.6</ymax>
    </bndbox>
  </object>
  <object>
    <name>Mango</name>
    <occluded>0</occluded>
    <bndbox>
      <xmin>57.7</xmin>
      <ymin>97.9</ymin>
      <xmax>153.1</xmax>
      <ymax>185.7</ymax>
    </bndbox>
  </object>
  <object>
    <name>Mango</name>
    <occluded>0</occluded>
    <bndbox>
      <xmin>0.0</xmin>
      <ymin>23.7</ymin>
      <xmax>75.4</xmax>
      <ymax>92.5</ymax>
    </bndbox>
  </object>
</annotation>
