<annotation>
  <folder>D:\Object_detection_data\obj\Peach_img</folder>
  <filename>Peach00405.png</filename>
  <path>D:\Object_detection_data\obj\Peach_img</path>
  <source>
    <database>Unknown</database>
  </source>
  <size>
    <width>480</width>
    <height>322</height>
    <depth/>
  </size>
  <segmented>0</segmented>
  <object>
    <name>Peach</name>
    <pose>Unspecified</pose>
    <truncated>0</truncated>
    <difficult>0</difficult>
    <bndbox>
      <xmin>340</xmin>
      <ymin>47</ymin>
      <xmax>443</xmax>
      <ymax>149</ymax>
    </bndbox>
  </object>
  <object>
    <name>Peach</name>
    <pose>Unspecified</pose>
    <truncated>0</truncated>
    <difficult>0</difficult>
    <bndbox>
      <xmin>1</xmin>
      <ymin>139</ymin>
      <xmax>118</xmax>
      <ymax>257</ymax>
    </bndbox>
  </object>
  <object>
    <name>Peach</name>
    <pose>Unspecified</pose>
    <truncated>0</truncated>
    <difficult>0</difficult>
    <bndbox>
      <xmin>29</xmin>
      <ymin>23</ymin>
      <xmax>133</xmax>
      <ymax>133</ymax>
    </bndbox>
  </object>
  <object>
    <name>Peach</name>
    <pose>Unspecified</pose>
    <truncated>0</truncated>
    <difficult>0</difficult>
    <bndbox>
      <xmin>250</xmin>
      <ymin>1</ymin>
      <xmax>363</xmax>
      <ymax>116</ymax>
    </bndbox>
  </object>
  <object>
    <name>Peach</name>
    <pose>Unspecified</pose>
    <truncated>0</truncated>
    <difficult>0</difficult>
    <bndbox>
      <xmin>119</xmin>
      <ymin>153</ymin>
      <xmax>232</xmax>
      <ymax>268</ymax>
    </bndbox>
  </object>
  <object>
    <name>Peach</name>
    <pose>Unspecified</pose>
    <truncated>0</truncated>
    <difficult>0</difficult>
    <bndbox>
      <xmin>162</xmin>
      <ymin>57</ymin>
      <xmax>260</xmax>
      <ymax>164</ymax>
    </bndbox>
  </object>
  <object>
    <name>Peach</name>
    <pose>Unspecified</pose>
    <truncated>0</truncated>
    <difficult>0</difficult>
    <bndbox>
      <xmin>271</xmin>
      <ymin>163</ymin>
      <xmax>379</xmax>
      <ymax>287</ymax>
    </bndbox>
  </object>
</annotation>
