<annotation>
  <folder>D:\Object_detection_data\obj\Peach_img</folder>
  <filename>Peach001290.png</filename>
  <path>D:\Object_detection_data\obj\Peach_img</path>
  <source>
    <database>Unknown</database>
  </source>
  <size>
    <width>320</width>
    <height>258</height>
    <depth/>
  </size>
  <segmented>0</segmented>
  <object>
    <name>Peach</name>
    <pose>Unspecified</pose>
    <truncated>0</truncated>
    <difficult>0</difficult>
    <bndbox>
      <xmin>142</xmin>
      <ymin>65</ymin>
      <xmax>221</xmax>
      <ymax>142</ymax>
    </bndbox>
  </object>
  <object>
    <name>Peach</name>
    <pose>Unspecified</pose>
    <truncated>0</truncated>
    <difficult>0</difficult>
    <bndbox>
      <xmin>129</xmin>
      <ymin>0</ymin>
      <xmax>206</xmax>
      <ymax>72</ymax>
    </bndbox>
  </object>
  <object>
    <name>Peach</name>
    <pose>Unspecified</pose>
    <truncated>0</truncated>
    <difficult>0</difficult>
    <bndbox>
      <xmin>134</xmin>
      <ymin>141</ymin>
      <xmax>234</xmax>
      <ymax>242</ymax>
    </bndbox>
  </object>
  <object>
    <name>Peach</name>
    <pose>Unspecified</pose>
    <truncated>0</truncated>
    <difficult>0</difficult>
    <bndbox>
      <xmin>24</xmin>
      <ymin>67</ymin>
      <xmax>98</xmax>
      <ymax>143</ymax>
    </bndbox>
  </object>
</annotation>
