<annotation>
  <folder>D:\Object_detection_data\obj\Peach_img</folder>
  <filename>Peach002153.png</filename>
  <path>D:\Object_detection_data\obj\Peach_img</path>
  <source>
    <database>Unknown</database>
  </source>
  <size>
    <width>320</width>
    <height>258</height>
    <depth/>
  </size>
  <segmented>0</segmented>
  <object>
    <name>Peach</name>
    <pose>Unspecified</pose>
    <truncated>0</truncated>
    <difficult>0</difficult>
    <bndbox>
      <xmin>147</xmin>
      <ymin>73</ymin>
      <xmax>223</xmax>
      <ymax>166</ymax>
    </bndbox>
  </object>
  <object>
    <name>Peach</name>
    <pose>Unspecified</pose>
    <truncated>0</truncated>
    <difficult>0</difficult>
    <bndbox>
      <xmin>231</xmin>
      <ymin>127</ymin>
      <xmax>316</xmax>
      <ymax>217</ymax>
    </bndbox>
  </object>
</annotation>
