<annotation>
  <folder>obj</folder>
  <filename>obj_train_data/247red applee03501247.png</filename>
  <source>
    <database>Unknown</database>
    <annotation>Unknown</annotation>
    <image>Unknown</image>
  </source>
  <size>
    <width>480</width>
    <height>322</height>
    <depth></depth>
  </size>
  <segmented>0</segmented>
  <object>
    <name>Apple</name>
    <occluded>0</occluded>
    <bndbox>
      <xmin>117.5</xmin>
      <ymin>125.6</ymin>
      <xmax>257.0</xmax>
      <ymax>253.1</ymax>
    </bndbox>
  </object>
  <object>
    <name>Apple</name>
    <occluded>0</occluded>
    <bndbox>
      <xmin>353.4</xmin>
      <ymin>132.5</ymin>
      <xmax>480.0</xmax>
      <ymax>236.6</ymax>
    </bndbox>
  </object>
  <object>
    <name>Apple</name>
    <occluded>0</occluded>
    <bndbox>
      <xmin>248.7</xmin>
      <ymin>144.5</ymin>
      <xmax>360.6</xmax>
      <ymax>263.5</ymax>
    </bndbox>
  </object>
  <object>
    <name>Apple</name>
    <occluded>0</occluded>
    <bndbox>
      <xmin>81.8</xmin>
      <ymin>40.7</ymin>
      <xmax>194.9</xmax>
      <ymax>147.5</ymax>
    </bndbox>
  </object>
  <object>
    <name>Apple</name>
    <occluded>0</occluded>
    <bndbox>
      <xmin>295.0</xmin>
      <ymin>40.7</ymin>
      <xmax>409.3</xmax>
      <ymax>148.7</ymax>
    </bndbox>
  </object>
  <object>
    <name>Apple</name>
    <occluded>0</occluded>
    <bndbox>
      <xmin>1.6</xmin>
      <ymin>5.6</ymin>
      <xmax>98.4</xmax>
      <ymax>102.5</ymax>
    </bndbox>
  </object>
  <object>
    <name>Apple</name>
    <occluded>0</occluded>
    <bndbox>
      <xmin>197.8</xmin>
      <ymin>26.0</ymin>
      <xmax>305.6</xmax>
      <ymax>138.0</ymax>
    </bndbox>
  </object>
</annotation>
