<annotation>
  <folder>obj</folder>
  <filename>obj_train_data/obj_train_data/Apple E0599.png</filename>
  <source>
    <database>Unknown</database>
    <annotation>Unknown</annotation>
    <image>Unknown</image>
  </source>
  <size>
    <width>320</width>
    <height>258</height>
    <depth></depth>
  </size>
  <segmented>0</segmented>
  <object>
    <name>Apple</name>
    <occluded>0</occluded>
    <bndbox>
      <xmin>43.8</xmin>
      <ymin>141.7</ymin>
      <xmax>111.6</xmax>
      <ymax>216.1</ymax>
    </bndbox>
  </object>
  <object>
    <name>Apple</name>
    <occluded>0</occluded>
    <bndbox>
      <xmin>192.7</xmin>
      <ymin>83.7</ymin>
      <xmax>265.1</xmax>
      <ymax>159.6</ymax>
    </bndbox>
  </object>
  <object>
    <name>Apple</name>
    <occluded>0</occluded>
    <bndbox>
      <xmin>178.4</xmin>
      <ymin>155.5</ymin>
      <xmax>247.1</xmax>
      <ymax>229.2</ymax>
    </bndbox>
  </object>
  <object>
    <name>Apple</name>
    <occluded>0</occluded>
    <bndbox>
      <xmin>129.9</xmin>
      <ymin>62.7</ymin>
      <xmax>193.5</xmax>
      <ymax>134.1</ymax>
    </bndbox>
  </object>
</annotation>
