<annotation>
  <folder></folder>
  <filename>Mango001550.png</filename>
  <source>
    <database>Unknown</database>
    <annotation>Unknown</annotation>
    <image>Unknown</image>
  </source>
  <size>
    <width>320</width>
    <height>258</height>
    <depth></depth>
  </size>
  <segmented>0</segmented>
  <object>
    <name>Mango</name>
    <occluded>0</occluded>
    <bndbox>
      <xmin>25.2</xmin>
      <ymin>67.3</ymin>
      <xmax>86.8</xmax>
      <ymax>160.8</ymax>
    </bndbox>
  </object>
  <object>
    <name>Mango</name>
    <occluded>0</occluded>
    <bndbox>
      <xmin>201.1</xmin>
      <ymin>59.4</ymin>
      <xmax>256.1</xmax>
      <ymax>166.1</ymax>
    </bndbox>
  </object>
  <object>
    <name>Mango</name>
    <occluded>0</occluded>
    <bndbox>
      <xmin>130.4</xmin>
      <ymin>48.0</ymin>
      <xmax>204.0</xmax>
      <ymax>160.7</ymax>
    </bndbox>
  </object>
</annotation>
